arm64_mask_gen_py-0.1.0.dist-info/METADATA
arm64_mask_gen_py-0.1.0.dist-info/WHEEL
arm64_mask_gen_py-0.1.0.dist-info/licenses/LICENSE
arm64_mask_gen_py.libs/libgcc_s-1e52349c.so.1
arm64_mask_gen_py.libs/libstdc++-e3b7606c.so.6
arm64_mask_gen_py/__init__.py
arm64_mask_gen_py/arm64_mask_gen_py.cpython-38-x86_64-linux-gnu.so
arm64_mask_gen_py-0.1.0.dist-info/RECORD
