Metadata-Version: 2.4
Name: arm64-mask-gen-py
Version: 0.1.0
Classifier: Development Status :: 4 - Beta
Classifier: Intended Audience :: Developers
Classifier: License :: OSI Approved :: MIT License
Classifier: Programming Language :: Python :: 3.8
Classifier: Programming Language :: Python :: 3.9
Classifier: Programming Language :: Python :: 3.10
Classifier: Programming Language :: Python :: 3.11
Classifier: Programming Language :: C++
Classifier: Topic :: Software Development :: Libraries :: Python Modules
Classifier: Operating System :: OS Independent
License-File: LICENSE
Author-email: Fran <fran@logicode.es>
License-Expression: MIT
Requires-Python: >=3.8
Project-URL: Homepage, https://github.com/xliee/arm64-mask-gen-py-wrapper
Project-URL: Repository, https://github.com/xliee/arm64-mask-gen-py-wrapper
